LICENSE
MANIFEST.in
README.md
example.py
requirements.txt
setup.cfg
setup.py
pysentipers/__init__.py
pysentipers/main.py
pysentipers/sentence.py
pysentipers/tag.py
pysentipers.egg-info/PKG-INFO
pysentipers.egg-info/SOURCES.txt
pysentipers.egg-info/dependency_links.txt
pysentipers.egg-info/requires.txt
pysentipers.egg-info/top_level.txt