Metadata-Version: 2.1
Name: pysentipers
Version: 0.1.7
Summary: Python API for SentiPers Dataset
Home-page: https://github.com/javadzarezadeh/pySentiPers
Author: Javad Zarezadeh
Author-email: jvd.zarezadeh@gmail.com
License: GPLv3
Keywords: sentipers sentiment analysis
Platform: UNKNOWN
Requires-Python: >=3
License-File: LICENSE
